ebook_converter/__init__.py
ebook_converter/constants.py
ebook_converter/constants_old.py
ebook_converter/logging.py
ebook_converter/main.py
ebook_converter/polyglot.py
ebook_converter/ptempfile.py
ebook_converter/css_selectors/__init__.py
ebook_converter/css_selectors/errors.py
ebook_converter/css_selectors/ordered_set.py
ebook_converter/css_selectors/parser.py
ebook_converter/css_selectors/select.py
ebook_converter/css_selectors/tests.py
ebook_converter/customize/__init__.py
ebook_converter/customize/builtins.py
ebook_converter/customize/conversion.py
ebook_converter/customize/profiles.py
ebook_converter/customize/ui.py
ebook_converter/data/default_tweaks.py
ebook_converter/data/fb2.xsl
ebook_converter/data/html.css
ebook_converter/data/iso_639-3.json
ebook_converter/data/lrf.xsl
ebook_converter/data/mime.types
ebook_converter/data/new_nav.html
ebook_converter/data/rtf.xsl
ebook_converter/data/jacket/stylesheet.css
ebook_converter/data/jacket/template.xhtml
ebook_converter/devices/__init__.py
ebook_converter/devices/interface.py
ebook_converter/ebooks/BeautifulSoup.py
ebook_converter/ebooks/__init__.py
ebook_converter/ebooks/chardet.py
ebook_converter/ebooks/covers.py
ebook_converter/ebooks/html_entities.py
ebook_converter/ebooks/compression/__init__.py
ebook_converter/ebooks/compression/palmdoc.py
ebook_converter/ebooks/conversion/__init__.py
ebook_converter/ebooks/conversion/cli.py
ebook_converter/ebooks/conversion/plumber.py
ebook_converter/ebooks/conversion/preprocess.py
ebook_converter/ebooks/conversion/utils.py
ebook_converter/ebooks/conversion/plugins/__init__.py
ebook_converter/ebooks/conversion/plugins/azw4_input.py
ebook_converter/ebooks/conversion/plugins/chm_input.py
ebook_converter/ebooks/conversion/plugins/comic_input.py
ebook_converter/ebooks/conversion/plugins/djvu_input.py
ebook_converter/ebooks/conversion/plugins/docx_input.py
ebook_converter/ebooks/conversion/plugins/docx_output.py
ebook_converter/ebooks/conversion/plugins/epub_input.py
ebook_converter_noimage-4.12.2.dist-info/LICENSE
ebook_converter_noimage-4.12.2.dist-info/METADATA
ebook_converter_noimage-4.12.2.dist-info/WHEEL
ebook_converter_noimage-4.12.2.dist-info/entry_points.txt
ebook_converter_noimage-4.12.2.dist-info/top_level.txt
ebook_converter_noimage-4.12.2.dist-info/RECORD
