Metadata-Version: 2.1
Name: ebook-converter-noimage
Version: 4.12.2
Summary: Convert ebook between different formats
Home-page: https://github.com/gryf/ebook-converter
Author: gryf
Author-email: gryf73@gmail.com
License: GPL3
Classifier: Environment :: Console
Classifier: Intended Audience :: Other Audience
Classifier: License :: OSI Approved :: GNU General Public License v3 (GPLv3)
Classifier: Operating System :: POSIX :: Linux
Classifier: Development Status :: 3 - Alpha
Classifier: Programming Language :: Python
Classifier: Programming Language :: Python :: 3
Classifier: Programming Language :: Python :: 3 :: Only
Classifier: Programming Language :: Python :: 3.6
Classifier: Programming Language :: Python :: 3.7
License-File: LICENSE
Requires-Dist: beautifulsoup4 (>=4.9.3)
Requires-Dist: css-parser (>=1.0.6)
Requires-Dist: filelock (>=3.0.12)
Requires-Dist: html2text (>=2020.1.16)
Requires-Dist: html5-parser (==0.4.9)
Requires-Dist: lxml
Requires-Dist: msgpack (>=1.0.0)
Requires-Dist: odfpy (>=1.4.1)
Requires-Dist: pillow (>=8.0.1)
Requires-Dist: python-dateutil (>=2.8.1)
Requires-Dist: setuptools (>=50.3.2)
Requires-Dist: tinycss (>=0.4)
